docs/__init__.py
docs/html_doc/__init__.py
docs/html_doc/conf.py
docs/html_doc/run_livereload.py
xai_compare/__init__.py
xai_compare/config.py
xai_compare/datasets.py
xai_compare/explainer_utilities.py
xai_compare/main.py
xai_compare/stam.py
xai_compare/abstract/__init__.py
xai_compare/abstract/comparison.py
xai_compare/abstract/explainer.py
xai_compare/comparisons/__init__.py
xai_compare/comparisons/consistency.py
xai_compare/comparisons/feature_selection.py
xai_compare/data/diabetes/diabetes.csv
xai_compare/data/german_credit_score/german_credit.csv
xai_compare/explainers/__init__.py
xai_compare/explainers/ebm_wrapper.py
xai_compare/explainers/lime_wrapper.py
xai_compare/explainers/permutation_wrapper.py
xai_compare/explainers/shap_wrapper.py
xai_compare/factories/__init__.py
xai_compare/factories/factory.py
xai_compare-0.1.2.dist-info/LICENSE
xai_compare-0.1.2.dist-info/METADATA
xai_compare-0.1.2.dist-info/WHEEL
xai_compare-0.1.2.dist-info/top_level.txt
xai_compare-0.1.2.dist-info/RECORD
