Metadata-Version: 2.1
Name: xai-compare
Version: 0.1.2
Summary: This repository aims to provide tools for comparing different explainability methods, enhancing the interpretation of machine learning models.
Home-page: https://github.com/emunaran/xai-compare.git
Author: Ran Emuna
Author-email: emuna.ran@gmail.com
Classifier: Programming Language :: Python :: 3
Classifier: License :: OSI Approved :: MIT License
Classifier: Operating System :: OS Independent
Requires-Python: >=3.9
License-File: LICENSE
Requires-Dist: jupyter ==1.0.0
Requires-Dist: lime ==0.2.0.1
Requires-Dist: matplotlib ==3.9.1
Requires-Dist: notebook ==7.2.1
Requires-Dist: numpy ==1.26.4
Requires-Dist: pandas ==2.2.2
Requires-Dist: scikit-learn ==1.5.1
Requires-Dist: scipy ==1.14.0
Requires-Dist: seaborn ==0.13.2
Requires-Dist: shap ==0.44.0
Requires-Dist: tqdm ==4.66.4
